kipp3
