Metadata-Version: 2.1
Name: kipp3
Version: 0.0.3
Summary: Python Utils
Home-page: https://github.com/Laisky/kipp
Author: Laisky
Author-email: ppcelery@gmail.com
License: MIT License
Keywords: setup,distutils,utils
Platform: UNKNOWN
Classifier: Development Status :: 4 - Beta
Classifier: Development Status :: 4 - Beta
Classifier: Topic :: Software Development :: Libraries
Classifier: Environment :: Web Environment
Classifier: Intended Audience :: Developers
Classifier: License :: OSI Approved :: MIT License
Classifier: Operating System :: OS Independent
Classifier: Programming Language :: Python
Classifier: Programming Language :: Python :: 3.6
Classifier: Programming Language :: Python :: 3.7
Classifier: Programming Language :: Python :: 3.8
Provides-Extra: test
Provides-Extra: doc
Provides-Extra: image
Provides-Extra: all
